conda_flow/__init__.py
conda_flow/commands.py
conda_flow/conda.py
conda_flow/config.py
conda_flow/shell.py
conda_flow/locks/op-env-linux-64.lock
conda_flow/locks/op-env-osx-64.lock
conda_flow-0.3.3.dist-info/LICENSE
conda_flow-0.3.3.dist-info/METADATA
conda_flow-0.3.3.dist-info/WHEEL
conda_flow-0.3.3.dist-info/entry_points.txt
conda_flow-0.3.3.dist-info/top_level.txt
conda_flow-0.3.3.dist-info/zip-safe
conda_flow-0.3.3.dist-info/RECORD
