Metadata-Version: 2.1
Name: conda-flow
Version: 0.3.3
Summary: Lockfile workflow utilities for conda
Home-page: https://git.ligo.org/james.kennington/conda-flow
Author: James Kennington
Author-email: james.kennington@ligo.org
License: MIT
Platform: UNKNOWN
Classifier: Development Status :: 3 - Alpha
Classifier: Intended Audience :: Science/Research
Classifier: Operating System :: OS Independent
Classifier: License :: OSI Approved :: MIT License
Classifier: Programming Language :: Python
Classifier: Programming Language :: Python :: 3
Classifier: Programming Language :: Python :: 3.7
Classifier: Programming Language :: Python :: 3.8
Classifier: Programming Language :: Python :: 3.9
Requires-Python: >=3.7
Requires-Dist: PyYaml (>=5.1)
Requires-Dist: cerberus
